gen2aclbundle/Gen2AclBundle.py
gen2aclbundle/Gen2AclBundleTest.py
gen2aclbundle/_config/.gitignore
gen2aclbundle/_config/config.yaml
gen2aclbundle/_config/config_test.yaml
gen2aclbundle/acl/AclConfigReader.py
gen2aclbundle/acl/AclPathResolver.py
gen2aclbundle/acl/check/AclCheckCommand.py
gen2aclbundle/acl/check/AclChecker.py
gen2aclbundle/acl/export/AclExportCommand.py
gen2aclbundle/acl/export/AclExporter.py
gen2aclbundle/acl/set/AclSetCommand.py
gen2aclbundle/acl/set/AclSetter.py
gen2aclbundle/acl/set/AclStringGenerator.py
gen2aclbundle/client/ServiceClientFactory.py
gen2_acl_bundle-0.2.1.dist-info/entry_points.txt
gen2_acl_bundle-0.2.1.dist-info/WHEEL
gen2_acl_bundle-0.2.1.dist-info/METADATA
gen2_acl_bundle-0.2.1.dist-info/RECORD
