Metadata-Version: 2.1
Name: gen2-acl-bundle
Version: 0.2.1
Summary: Azure DataLake ACL setup bundle for the Pyfony Framework
Home-page: https://github.com/bricksflow/gen2-acl-bundle
License: MIT
Author: Jiri Koutny
Author-email: jiri.koutny@datasentics.com
Requires-Python: >=3.7,<4.0
Classifier: License :: OSI Approved :: MIT License
Classifier: Operating System :: OS Independent
Classifier: Programming Language :: Python :: 3
Classifier: Programming Language :: Python :: 3.7
Classifier: Programming Language :: Python :: 3.8
Classifier: Programming Language :: Python :: 3.9
Requires-Dist: azure-storage-file-datalake (>=12.0,<13.0)
Requires-Dist: console-bundle (>=0.3.1,<0.4.0)
Requires-Dist: pandas (>=0.25.0,<0.26.0)
Requires-Dist: pyfony-bundles (>=0.3.2,<0.4.0)
Project-URL: Repository, https://github.com/bricksflow/gen2-acl-bundle
